{
  "db_name": "PostgreSQL",
  "query": "\n            SELECT listed_by, state\n            FROM listings\n            WHERE id = $1 AND deleted_at IS NULL\n            FOR UPDATE\n        ",
  "describe": {
    "columns": [
      {
        "ordinal": 0,
        "name": "listed_by",
        "type_info": "Uuid",
        "origin": {
          "Table": {
            "table": "listings",
            "name": "listed_by"
          }
        }
      },
      {
        "ordinal": 1,
        "name": "state",
        "type_info": "Text",
        "origin": {
          "Table": {
            "table": "listings",
            "name": "state"
          }
        }
      }
    ],
    "parameters": {
      "Left": [
        "Uuid"
      ]
    },
    "nullable": [
      false,
      false
    ]
  },
  "hash": "935bf4f455663f778634e08fe9e8eb22ac2ab27c9db08715c3a20acedaa26396"
}
