{
  "db_name": "PostgreSQL",
  "query": "\n            UPDATE users\n            SET email_verified = TRUE, updated_at = NOW()\n            WHERE id = $1 AND email_verified = FALSE AND deleted_at IS NULL\n            RETURNING id\n        ",
  "describe": {
    "columns": [
      {
        "ordinal": 0,
        "name": "id",
        "type_info": "Uuid",
        "origin": {
          "Table": {
            "table": "users",
            "name": "id"
          }
        }
      }
    ],
    "parameters": {
      "Left": [
        "Uuid"
      ]
    },
    "nullable": [
      false
    ]
  },
  "hash": "78ae4861f8ca7bec7cf1a686c2d66e157f9b44651ed0fef1d3e682b162dcb26d"
}
