{
  "db_name": "PostgreSQL",
  "query": "\n            SELECT price\n            FROM ico_schedules\n            WHERE start_timestamp <= EXTRACT(EPOCH FROM NOW())::BIGINT * 1000\n            ORDER BY start_timestamp DESC\n            LIMIT 1\n        ",
  "describe": {
    "columns": [
      {
        "ordinal": 0,
        "name": "price",
        "type_info": "Text"
      }
    ],
    "parameters": {
      "Left": []
    },
    "nullable": [
      false
    ]
  },
  "hash": "fd37cdbb54f702c4f47f52576cf2f1f000205edb1684fdb89c42c98007a9e954"
}
